<?xml version="1.0"?>	
-<soap:Envelope xmlns:xsi="http://www.w3.org/2001/XMLSchema-instance"
             	xmlns:xsd="http://www.w3.org/2001/XMLSchema"
             	xmlns:soap="http://schemas.xmlsoap.org/soap/envelope/">
	-<soap:Header>
		-<technicalHeader xmlns="http://services.axa.gulf/schemas/technical">
			<callerName>OLS</callerName>
			<auditTimestamp>2019-10-10T12:16:17.8173072Z</auditTimestamp>
			-<messageMetadata>
				<serviceID>GetPolicyDetails</serviceID>
				<serviceName>GetPolicyDetails</serviceName>
				<serviceOperation>GetPolicyDetails</serviceOperation>
				<serviceVersion>1.0</serviceVersion>
			</messageMetadata>
			-<requesters>
				<opCo>KSA</opCo>
			</requesters>
			-<users>
				<userId>TEST</userId>
			</users>
		</technicalHeader>
	</soap:Header>
	<soap:Body>
		<MainPolicy>
			<ID>2292608896</ID>
			<name>NASEER US ZAMA SYED</name>
			<gender>M</gender>
			<policyNumber>1/XN/3693/1/0</policyNumber>
			<membershipnumber>383/0</membershipnumber>
			<maritalstatus>M</maritalstatus>
			<network>1</network>
			<dateofbirth>13/06/1985</dateofbirth>
			<employeeid>44000727</employeeid>
			<policyholder>NASEER US ZAMA SYED</policyholder>
			<benefits>AXA201 PRIVATE</benefits>
			<issuedate>05/10/2019</issuedate>
			<expirydate>04/10/2020</expirydate>
			<areaofcover>Local</areaofcover>
			<hospital>20% Max100</hospital>
			<clinic>20% Max100</clinic>
			<lower>20% Max100</lower>
			<CCHIstatus>PENDING</CCHIstatus>
			<reasonofrejection/>
		</MainPolicy>
		<dependents/>
	</soap:Body>
</soap:Envelope>
